django_discord/py/__init__.py
django_discord/py/__main__.py
django_discord/py/exceptions.py
django_discord/py/bot/__init__.py
django_discord/py/bot/apps.py
django_discord/py/bot/basic_bot.py
django_discord/py/bot/consumers.py
django_discord/py/bot/signals.py
django_discord/py/cli/__init__.py
django_discord/py/configuration/__init__.py
django_discord/py/configuration/asgi.py
django_discord/py/configuration/urls.py
django_discord/py/configuration/wsgi.py
django_discord/py/configuration/common_components/__init__.py
django_discord/py/configuration/common_components/base.py
django_discord/py/configuration/common_components/channels.py
django_discord/py/configuration/common_components/django_extensions.py
django_discord/py/configuration/http_settings/__init__.py
django_discord/py/configuration/http_settings/components/__init__.py
django_discord/py/configuration/worker_settings/__init__.py
django_discord/py/configuration/worker_settings/components/__init__.py
django_discord/py/configuration/worker_settings/components/discord.py
django_discord/py/configuration/worker_settings/components/worker_apps.py
django_discord/py/entrypoints/__init__.py
django_discord/py/entrypoints/channels_entrypoint.py
django_discord/py/entrypoints/http_entrypoint.py
django_discord/py/example_bot/__init__.py
django_discord/py/example_bot/bot_plugins.py
django_discord/py/plugins/__init__.py
django_discord/py/plugins/datatypes.py
django_discord_py-2023.301.243.dist-info/LICENSE.txt
django_discord_py-2023.301.243.dist-info/METADATA
django_discord_py-2023.301.243.dist-info/WHEEL
django_discord_py-2023.301.243.dist-info/entry_points.txt
django_discord_py-2023.301.243.dist-info/top_level.txt
django_discord_py-2023.301.243.dist-info/RECORD
