Metadata-Version: 2.1
Name: django-discord-py
Version: 2023.301.243
Summary: Easy to use, easy to setup discord bots with django integration
Home-page: https://github.com/MrSage/django_discord.py
Author: Collin Sage
Author-email: 3229549+MrSage@users.noreply.github.com
License: MIT
Project-URL: Documentation, https://github.com/MrSage/django_discord.py
Platform: any
Classifier: Development Status :: 4 - Beta
Classifier: Programming Language :: Python
License-File: LICENSE.txt
Requires-Dist: channels[daphne]
Requires-Dist: channels-redis
Requires-Dist: discord.py
Requires-Dist: django
Requires-Dist: django-extensions
Requires-Dist: django-split-settings
Requires-Dist: ipython
Requires-Dist: importlib-metadata ; python_version < "3.11"
Provides-Extra: testing
Requires-Dist: setuptools ; extra == 'testing'
Requires-Dist: pytest ; extra == 'testing'
Requires-Dist: pytest-cov ; extra == 'testing'
